doc_extractor/__init__.py
doc_extractor/extract.py
doc_extractor-0.2.3.dist-info/WHEEL
doc_extractor-0.2.3.dist-info/METADATA
doc_extractor-0.2.3.dist-info/RECORD
