Metadata-Version: 2.1
Name: doc-extractor
Version: 0.2.3
Summary: 
Author: Aditya Varma Uddaraju
Author-email: adithya951@gmail.com
Requires-Python: >=3.10,<4.0
Classifier: Programming Language :: Python :: 3
Classifier: Programming Language :: Python :: 3.10
Classifier: Programming Language :: Python :: 3.11
Requires-Dist: docx2txt (>=0.8,<0.9)
Requires-Dist: html2text (>=2020.1.16,<2021.0.0)
Requires-Dist: pdfplumber (>=0.7.6,<0.8.0)
Requires-Dist: pymupdf (>=1.21.1,<2.0.0)
Requires-Dist: pypdf2 (>=3.0.1,<4.0.0)
Requires-Dist: tika (>=2.6.0,<3.0.0)
